<?xml version="1.0" ?>
<annotation>
<folder>JPEGImages</folder>
<filename>14824.png</filename>
<path>E:\hand_bone_data\voc\VOCdevkit\VOC2007\JPEGImages\14824.png</path>
<source>
    <database>Unknown</database>
</source>
<size>
    <width>1216</width>
    <height>1622</height>
    <depth>3</depth>
</size>

<segmented>0</segmented>
    <object>
    <name>MiddlePhalanx</name>
    <pose>Unspecified</pose>
    <truncated>0</truncated>
    <difficult>0</difficult>
    <bndbox>
        <xmin>650</xmin>
        <ymin>378</ymin>
        <xmax>783</xmax>
        <ymax>508</ymax>
    </bndbox>
</object>
    <object>
    <name>MiddlePhalanx</name>
    <pose>Unspecified</pose>
    <truncated>0</truncated>
    <difficult>0</difficult>
    <bndbox>
        <xmin>479</xmin>
        <ymin>334</ymin>
        <xmax>601</xmax>
        <ymax>460</ymax>
    </bndbox>
</object>
    <object>
    <name>MiddlePhalanx</name>
    <pose>Unspecified</pose>
    <truncated>0</truncated>
    <difficult>0</difficult>
    <bndbox>
        <xmin>275</xmin>
        <ymin>404</ymin>
        <xmax>435</xmax>
        <ymax>530</ymax>
    </bndbox>
</object>
    <object>
    <name>MiddlePhalanx</name>
    <pose>Unspecified</pose>
    <truncated>0</truncated>
    <difficult>0</difficult>
    <bndbox>
        <xmin>133</xmin>
        <ymin>545</ymin>
        <xmax>267</xmax>
        <ymax>656</ymax>
    </bndbox>
</object>
    <object>
    <name>DistalPhalanx</name>
    <pose>Unspecified</pose>
    <truncated>0</truncated>
    <difficult>0</difficult>
    <bndbox>
        <xmin>670</xmin>
        <ymin>207</ymin>
        <xmax>802</xmax>
        <ymax>369</ymax>
    </bndbox>
</object>
    <object>
    <name>DistalPhalanx</name>
    <pose>Unspecified</pose>
    <truncated>0</truncated>
    <difficult>0</difficult>
    <bndbox>
        <xmin>494</xmin>
        <ymin>134</ymin>
        <xmax>627</xmax>
        <ymax>300</ymax>
    </bndbox>
</object>
    <object>
    <name>DistalPhalanx</name>
    <pose>Unspecified</pose>
    <truncated>0</truncated>
    <difficult>0</difficult>
    <bndbox>
        <xmin>227</xmin>
        <ymin>204</ymin>
        <xmax>384</xmax>
        <ymax>370</ymax>
    </bndbox>
</object>
    <object>
    <name>DistalPhalanx</name>
    <pose>Unspecified</pose>
    <truncated>0</truncated>
    <difficult>0</difficult>
    <bndbox>
        <xmin>57</xmin>
        <ymin>378</ymin>
        <xmax>183</xmax>
        <ymax>552</ymax>
    </bndbox>
</object>
    <object>
    <name>DistalPhalanx</name>
    <pose>Unspecified</pose>
    <truncated>0</truncated>
    <difficult>0</difficult>
    <bndbox>
        <xmin>887</xmin>
        <ymin>661</ymin>
        <xmax>1035</xmax>
        <ymax>816</ymax>
    </bndbox>
</object>
    <object>
    <name>ProximalPhalanx</name>
    <pose>Unspecified</pose>
    <truncated>0</truncated>
    <difficult>0</difficult>
    <bndbox>
        <xmin>592</xmin>
        <ymin>470</ymin>
        <xmax>714</xmax>
        <ymax>692</ymax>
    </bndbox>
</object>
    <object>
    <name>ProximalPhalanx</name>
    <pose>Unspecified</pose>
    <truncated>0</truncated>
    <difficult>0</difficult>
    <bndbox>
        <xmin>457</xmin>
        <ymin>474</ymin>
        <xmax>564</xmax>
        <ymax>693</ymax>
    </bndbox>
</object>
    <object>
    <name>ProximalPhalanx</name>
    <pose>Unspecified</pose>
    <truncated>0</truncated>
    <difficult>0</difficult>
    <bndbox>
        <xmin>331</xmin>
        <ymin>537</ymin>
        <xmax>435</xmax>
        <ymax>745</ymax>
    </bndbox>
</object>
    <object>
    <name>ProximalPhalanx</name>
    <pose>Unspecified</pose>
    <truncated>0</truncated>
    <difficult>0</difficult>
    <bndbox>
        <xmin>209</xmin>
        <ymin>623</ymin>
        <xmax>327</xmax>
        <ymax>782</ymax>
    </bndbox>
</object>
    <object>
    <name>MCP</name>
    <pose>Unspecified</pose>
    <truncated>0</truncated>
    <difficult>0</difficult>
    <bndbox>
        <xmin>272</xmin>
        <ymin>730</ymin>
        <xmax>372</xmax>
        <ymax>941</ymax>
    </bndbox>
</object>
    <object>
    <name>MCP</name>
    <pose>Unspecified</pose>
    <truncated>0</truncated>
    <difficult>0</difficult>
    <bndbox>
        <xmin>361</xmin>
        <ymin>708</ymin>
        <xmax>457</xmax>
        <ymax>878</ymax>
    </bndbox>
</object>
    <object>
    <name>MCP</name>
    <pose>Unspecified</pose>
    <truncated>0</truncated>
    <difficult>0</difficult>
    <bndbox>
        <xmin>448</xmin>
        <ymin>651</ymin>
        <xmax>555</xmax>
        <ymax>895</ymax>
    </bndbox>
</object>
    <object>
    <name>MCP</name>
    <pose>Unspecified</pose>
    <truncated>0</truncated>
    <difficult>0</difficult>
    <bndbox>
        <xmin>575</xmin>
        <ymin>649</ymin>
        <xmax>679</xmax>
        <ymax>849</ymax>
    </bndbox>
</object>
    <object>
    <name>ProximalPhalanx</name>
    <pose>Unspecified</pose>
    <truncated>0</truncated>
    <difficult>0</difficult>
    <bndbox>
        <xmin>764</xmin>
        <ymin>804</ymin>
        <xmax>901</xmax>
        <ymax>952</ymax>
    </bndbox>
</object>
    <object>
    <name>MCPFirst</name>
    <pose>Unspecified</pose>
    <truncated>0</truncated>
    <difficult>0</difficult>
    <bndbox>
        <xmin>566</xmin>
        <ymin>914</ymin>
        <xmax>781</xmax>
        <ymax>1111</ymax>
    </bndbox>
</object>
    <object>
    <name>Ulna</name>
    <pose>Unspecified</pose>
    <truncated>0</truncated>
    <difficult>0</difficult>
    <bndbox>
        <xmin>279</xmin>
        <ymin>1156</ymin>
        <xmax>427</xmax>
        <ymax>1400</ymax>
    </bndbox>
</object>
    <object>
    <name>Radius</name>
    <pose>Unspecified</pose>
    <truncated>0</truncated>
    <difficult>0</difficult>
    <bndbox>
        <xmin>409</xmin>
        <ymin>1126</ymin>
        <xmax>598</xmax>
        <ymax>1397</ymax>
    </bndbox>
</object>
</annotation>
