<?xml version="1.0" ?>
<annotation>
<folder>JPEGImages</folder>
<filename>1996.png</filename>
<path>E:\hand_bone_data\voc\VOCdevkit\VOC2007\JPEGImages\1996.png</path>
<source>
    <database>Unknown</database>
</source>
<size>
    <width>2040</width>
    <height>2570</height>
    <depth>3</depth>
</size>

<segmented>0</segmented>
    <object>
    <name>Radius</name>
    <pose>Unspecified</pose>
    <truncated>0</truncated>
    <difficult>0</difficult>
    <bndbox>
        <xmin>901</xmin>
        <ymin>1665</ymin>
        <xmax>1126</xmax>
        <ymax>1982</ymax>
    </bndbox>
</object>
    <object>
    <name>Ulna</name>
    <pose>Unspecified</pose>
    <truncated>0</truncated>
    <difficult>0</difficult>
    <bndbox>
        <xmin>741</xmin>
        <ymin>1668</ymin>
        <xmax>915</xmax>
        <ymax>2012</ymax>
    </bndbox>
</object>
    <object>
    <name>MCPFirst</name>
    <pose>Unspecified</pose>
    <truncated>0</truncated>
    <difficult>0</difficult>
    <bndbox>
        <xmin>1145</xmin>
        <ymin>1418</ymin>
        <xmax>1345</xmax>
        <ymax>1659</ymax>
    </bndbox>
</object>
    <object>
    <name>ProximalPhalanx</name>
    <pose>Unspecified</pose>
    <truncated>0</truncated>
    <difficult>0</difficult>
    <bndbox>
        <xmin>1352</xmin>
        <ymin>1287</ymin>
        <xmax>1498</xmax>
        <ymax>1454</ymax>
    </bndbox>
</object>
    <object>
    <name>ProximalPhalanx</name>
    <pose>Unspecified</pose>
    <truncated>0</truncated>
    <difficult>0</difficult>
    <bndbox>
        <xmin>1167</xmin>
        <ymin>965</ymin>
        <xmax>1313</xmax>
        <ymax>1157</ymax>
    </bndbox>
</object>
    <object>
    <name>ProximalPhalanx</name>
    <pose>Unspecified</pose>
    <truncated>0</truncated>
    <difficult>0</difficult>
    <bndbox>
        <xmin>991</xmin>
        <ymin>964</ymin>
        <xmax>1137</xmax>
        <ymax>1151</ymax>
    </bndbox>
</object>
    <object>
    <name>ProximalPhalanx</name>
    <pose>Unspecified</pose>
    <truncated>0</truncated>
    <difficult>0</difficult>
    <bndbox>
        <xmin>851</xmin>
        <ymin>1011</ymin>
        <xmax>976</xmax>
        <ymax>1198</ymax>
    </bndbox>
</object>
    <object>
    <name>ProximalPhalanx</name>
    <pose>Unspecified</pose>
    <truncated>0</truncated>
    <difficult>0</difficult>
    <bndbox>
        <xmin>713</xmin>
        <ymin>1123</ymin>
        <xmax>834</xmax>
        <ymax>1248</ymax>
    </bndbox>
</object>
    <object>
    <name>MCP</name>
    <pose>Unspecified</pose>
    <truncated>0</truncated>
    <difficult>0</difficult>
    <bndbox>
        <xmin>755</xmin>
        <ymin>1211</ymin>
        <xmax>867</xmax>
        <ymax>1436</ymax>
    </bndbox>
</object>
    <object>
    <name>MCP</name>
    <pose>Unspecified</pose>
    <truncated>0</truncated>
    <difficult>0</difficult>
    <bndbox>
        <xmin>876</xmin>
        <ymin>1153</ymin>
        <xmax>980</xmax>
        <ymax>1357</ymax>
    </bndbox>
</object>
    <object>
    <name>MCP</name>
    <pose>Unspecified</pose>
    <truncated>0</truncated>
    <difficult>0</difficult>
    <bndbox>
        <xmin>992</xmin>
        <ymin>1119</ymin>
        <xmax>1121</xmax>
        <ymax>1328</ymax>
    </bndbox>
</object>
    <object>
    <name>MCP</name>
    <pose>Unspecified</pose>
    <truncated>0</truncated>
    <difficult>0</difficult>
    <bndbox>
        <xmin>1134</xmin>
        <ymin>1119</ymin>
        <xmax>1276</xmax>
        <ymax>1344</ymax>
    </bndbox>
</object>
    <object>
    <name>DistalPhalanx</name>
    <pose>Unspecified</pose>
    <truncated>0</truncated>
    <difficult>0</difficult>
    <bndbox>
        <xmin>1451</xmin>
        <ymin>1157</ymin>
        <xmax>1667</xmax>
        <ymax>1344</ymax>
    </bndbox>
</object>
    <object>
    <name>DistalPhalanx</name>
    <pose>Unspecified</pose>
    <truncated>0</truncated>
    <difficult>0</difficult>
    <bndbox>
        <xmin>1246</xmin>
        <ymin>619</ymin>
        <xmax>1401</xmax>
        <ymax>828</ymax>
    </bndbox>
</object>
    <object>
    <name>DistalPhalanx</name>
    <pose>Unspecified</pose>
    <truncated>0</truncated>
    <difficult>0</difficult>
    <bndbox>
        <xmin>1034</xmin>
        <ymin>548</ymin>
        <xmax>1151</xmax>
        <ymax>740</ymax>
    </bndbox>
</object>
    <object>
    <name>DistalPhalanx</name>
    <pose>Unspecified</pose>
    <truncated>0</truncated>
    <difficult>0</difficult>
    <bndbox>
        <xmin>830</xmin>
        <ymin>615</ymin>
        <xmax>959</xmax>
        <ymax>811</ymax>
    </bndbox>
</object>
    <object>
    <name>DistalPhalanx</name>
    <pose>Unspecified</pose>
    <truncated>0</truncated>
    <difficult>0</difficult>
    <bndbox>
        <xmin>584</xmin>
        <ymin>836</ymin>
        <xmax>701</xmax>
        <ymax>990</ymax>
    </bndbox>
</object>
    <object>
    <name>MiddlePhalanx</name>
    <pose>Unspecified</pose>
    <truncated>0</truncated>
    <difficult>0</difficult>
    <bndbox>
        <xmin>630</xmin>
        <ymin>994</ymin>
        <xmax>755</xmax>
        <ymax>1128</ymax>
    </bndbox>
</object>
    <object>
    <name>MiddlePhalanx</name>
    <pose>Unspecified</pose>
    <truncated>0</truncated>
    <difficult>0</difficult>
    <bndbox>
        <xmin>826</xmin>
        <ymin>832</ymin>
        <xmax>967</xmax>
        <ymax>965</ymax>
    </bndbox>
</object>
    <object>
    <name>MiddlePhalanx</name>
    <pose>Unspecified</pose>
    <truncated>0</truncated>
    <difficult>0</difficult>
    <bndbox>
        <xmin>1005</xmin>
        <ymin>778</ymin>
        <xmax>1159</xmax>
        <ymax>903</ymax>
    </bndbox>
</object>
    <object>
    <name>MiddlePhalanx</name>
    <pose>Unspecified</pose>
    <truncated>0</truncated>
    <difficult>0</difficult>
    <bndbox>
        <xmin>1217</xmin>
        <ymin>819</ymin>
        <xmax>1363</xmax>
        <ymax>944</ymax>
    </bndbox>
</object>
</annotation>
