<?xml version="1.0" ?>
<annotation>
<folder>JPEGImages</folder>
<filename>2225.png</filename>
<path>E:\hand_bone_data\voc\VOCdevkit\VOC2007\JPEGImages\2225.png</path>
<source>
    <database>Unknown</database>
</source>
<size>
    <width>800</width>
    <height>1339</height>
    <depth>3</depth>
</size>

<segmented>0</segmented>
    <object>
    <name>Radius</name>
    <pose>Unspecified</pose>
    <truncated>0</truncated>
    <difficult>0</difficult>
    <bndbox>
        <xmin>252</xmin>
        <ymin>1067</ymin>
        <xmax>425</xmax>
        <ymax>1277</ymax>
    </bndbox>
</object>
    <object>
    <name>Ulna</name>
    <pose>Unspecified</pose>
    <truncated>0</truncated>
    <difficult>0</difficult>
    <bndbox>
        <xmin>166</xmin>
        <ymin>1028</ymin>
        <xmax>271</xmax>
        <ymax>1249</ymax>
    </bndbox>
</object>
    <object>
    <name>MCPFirst</name>
    <pose>Unspecified</pose>
    <truncated>0</truncated>
    <difficult>0</difficult>
    <bndbox>
        <xmin>386</xmin>
        <ymin>916</ymin>
        <xmax>593</xmax>
        <ymax>1069</ymax>
    </bndbox>
</object>
    <object>
    <name>MCP</name>
    <pose>Unspecified</pose>
    <truncated>0</truncated>
    <difficult>0</difficult>
    <bndbox>
        <xmin>398</xmin>
        <ymin>664</ymin>
        <xmax>503</xmax>
        <ymax>827</ymax>
    </bndbox>
</object>
    <object>
    <name>MCP</name>
    <pose>Unspecified</pose>
    <truncated>0</truncated>
    <difficult>0</difficult>
    <bndbox>
        <xmin>300</xmin>
        <ymin>654</ymin>
        <xmax>391</xmax>
        <ymax>827</ymax>
    </bndbox>
</object>
    <object>
    <name>MCP</name>
    <pose>Unspecified</pose>
    <truncated>0</truncated>
    <difficult>0</difficult>
    <bndbox>
        <xmin>228</xmin>
        <ymin>681</ymin>
        <xmax>313</xmax>
        <ymax>833</ymax>
    </bndbox>
</object>
    <object>
    <name>MCP</name>
    <pose>Unspecified</pose>
    <truncated>0</truncated>
    <difficult>0</difficult>
    <bndbox>
        <xmin>161</xmin>
        <ymin>705</ymin>
        <xmax>249</xmax>
        <ymax>877</ymax>
    </bndbox>
</object>
    <object>
    <name>ProximalPhalanx</name>
    <pose>Unspecified</pose>
    <truncated>0</truncated>
    <difficult>0</difficult>
    <bndbox>
        <xmin>510</xmin>
        <ymin>786</ymin>
        <xmax>655</xmax>
        <ymax>908</ymax>
    </bndbox>
</object>
    <object>
    <name>ProximalPhalanx</name>
    <pose>Unspecified</pose>
    <truncated>0</truncated>
    <difficult>0</difficult>
    <bndbox>
        <xmin>408</xmin>
        <ymin>559</ymin>
        <xmax>516</xmax>
        <ymax>701</ymax>
    </bndbox>
</object>
    <object>
    <name>ProximalPhalanx</name>
    <pose>Unspecified</pose>
    <truncated>0</truncated>
    <difficult>0</difficult>
    <bndbox>
        <xmin>300</xmin>
        <ymin>555</ymin>
        <xmax>408</xmax>
        <ymax>698</ymax>
    </bndbox>
</object>
    <object>
    <name>ProximalPhalanx</name>
    <pose>Unspecified</pose>
    <truncated>0</truncated>
    <difficult>0</difficult>
    <bndbox>
        <xmin>215</xmin>
        <ymin>576</ymin>
        <xmax>316</xmax>
        <ymax>711</ymax>
    </bndbox>
</object>
    <object>
    <name>ProximalPhalanx</name>
    <pose>Unspecified</pose>
    <truncated>0</truncated>
    <difficult>0</difficult>
    <bndbox>
        <xmin>130</xmin>
        <ymin>644</ymin>
        <xmax>228</xmax>
        <ymax>759</ymax>
    </bndbox>
</object>
    <object>
    <name>DistalPhalanx</name>
    <pose>Unspecified</pose>
    <truncated>0</truncated>
    <difficult>0</difficult>
    <bndbox>
        <xmin>598</xmin>
        <ymin>654</ymin>
        <xmax>747</xmax>
        <ymax>800</ymax>
    </bndbox>
</object>
    <object>
    <name>DistalPhalanx</name>
    <pose>Unspecified</pose>
    <truncated>0</truncated>
    <difficult>0</difficult>
    <bndbox>
        <xmin>466</xmin>
        <ymin>281</ymin>
        <xmax>581</xmax>
        <ymax>444</ymax>
    </bndbox>
</object>
    <object>
    <name>DistalPhalanx</name>
    <pose>Unspecified</pose>
    <truncated>0</truncated>
    <difficult>0</difficult>
    <bndbox>
        <xmin>337</xmin>
        <ymin>250</ymin>
        <xmax>435</xmax>
        <ymax>379</ymax>
    </bndbox>
</object>
    <object>
    <name>DistalPhalanx</name>
    <pose>Unspecified</pose>
    <truncated>0</truncated>
    <difficult>0</difficult>
    <bndbox>
        <xmin>215</xmin>
        <ymin>284</ymin>
        <xmax>330</xmax>
        <ymax>406</ymax>
    </bndbox>
</object>
    <object>
    <name>DistalPhalanx</name>
    <pose>Unspecified</pose>
    <truncated>0</truncated>
    <difficult>0</difficult>
    <bndbox>
        <xmin>83</xmin>
        <ymin>406</ymin>
        <xmax>177</xmax>
        <ymax>515</ymax>
    </bndbox>
</object>
    <object>
    <name>MiddlePhalanx</name>
    <pose>Unspecified</pose>
    <truncated>0</truncated>
    <difficult>0</difficult>
    <bndbox>
        <xmin>103</xmin>
        <ymin>528</ymin>
        <xmax>215</xmax>
        <ymax>630</ymax>
    </bndbox>
</object>
    <object>
    <name>MiddlePhalanx</name>
    <pose>Unspecified</pose>
    <truncated>0</truncated>
    <difficult>0</difficult>
    <bndbox>
        <xmin>215</xmin>
        <ymin>444</ymin>
        <xmax>327</xmax>
        <ymax>549</ymax>
    </bndbox>
</object>
    <object>
    <name>MiddlePhalanx</name>
    <pose>Unspecified</pose>
    <truncated>0</truncated>
    <difficult>0</difficult>
    <bndbox>
        <xmin>327</xmin>
        <ymin>420</ymin>
        <xmax>432</xmax>
        <ymax>518</ymax>
    </bndbox>
</object>
    <object>
    <name>MiddlePhalanx</name>
    <pose>Unspecified</pose>
    <truncated>0</truncated>
    <difficult>0</difficult>
    <bndbox>
        <xmin>445</xmin>
        <ymin>447</ymin>
        <xmax>574</xmax>
        <ymax>555</ymax>
    </bndbox>
</object>
</annotation>
