<?xml version="1.0" ?>
<annotation>
<folder>JPEGImages</folder>
<filename>2490.png</filename>
<path>E:\hand_bone_data\voc\VOCdevkit\VOC2007\JPEGImages\2490.png</path>
<source>
    <database>Unknown</database>
</source>
<size>
    <width>905</width>
    <height>1204</height>
    <depth>3</depth>
</size>

<segmented>0</segmented>
    <object>
    <name>Radius</name>
    <pose>Unspecified</pose>
    <truncated>0</truncated>
    <difficult>0</difficult>
    <bndbox>
        <xmin>355</xmin>
        <ymin>872</ymin>
        <xmax>535</xmax>
        <ymax>1123</ymax>
    </bndbox>
</object>
    <object>
    <name>Ulna</name>
    <pose>Unspecified</pose>
    <truncated>0</truncated>
    <difficult>0</difficult>
    <bndbox>
        <xmin>253</xmin>
        <ymin>898</ymin>
        <xmax>385</xmax>
        <ymax>1101</ymax>
    </bndbox>
</object>
    <object>
    <name>MCPFirst</name>
    <pose>Unspecified</pose>
    <truncated>0</truncated>
    <difficult>0</difficult>
    <bndbox>
        <xmin>511</xmin>
        <ymin>661</ymin>
        <xmax>694</xmax>
        <ymax>854</ymax>
    </bndbox>
</object>
    <object>
    <name>MCP</name>
    <pose>Unspecified</pose>
    <truncated>0</truncated>
    <difficult>0</difficult>
    <bndbox>
        <xmin>490</xmin>
        <ymin>454</ymin>
        <xmax>592</xmax>
        <ymax>637</ymax>
    </bndbox>
</object>
    <object>
    <name>MCP</name>
    <pose>Unspecified</pose>
    <truncated>0</truncated>
    <difficult>0</difficult>
    <bndbox>
        <xmin>375</xmin>
        <ymin>457</ymin>
        <xmax>490</xmax>
        <ymax>667</ymax>
    </bndbox>
</object>
    <object>
    <name>MCP</name>
    <pose>Unspecified</pose>
    <truncated>0</truncated>
    <difficult>0</difficult>
    <bndbox>
        <xmin>289</xmin>
        <ymin>494</ymin>
        <xmax>387</xmax>
        <ymax>684</ymax>
    </bndbox>
</object>
    <object>
    <name>MCP</name>
    <pose>Unspecified</pose>
    <truncated>0</truncated>
    <difficult>0</difficult>
    <bndbox>
        <xmin>202</xmin>
        <ymin>549</ymin>
        <xmax>297</xmax>
        <ymax>708</ymax>
    </bndbox>
</object>
    <object>
    <name>ProximalPhalanx</name>
    <pose>Unspecified</pose>
    <truncated>0</truncated>
    <difficult>0</difficult>
    <bndbox>
        <xmin>635</xmin>
        <ymin>523</ymin>
        <xmax>777</xmax>
        <ymax>679</ymax>
    </bndbox>
</object>
    <object>
    <name>ProximalPhalanx</name>
    <pose>Unspecified</pose>
    <truncated>0</truncated>
    <difficult>0</difficult>
    <bndbox>
        <xmin>497</xmin>
        <ymin>359</ymin>
        <xmax>626</xmax>
        <ymax>501</ymax>
    </bndbox>
</object>
    <object>
    <name>ProximalPhalanx</name>
    <pose>Unspecified</pose>
    <truncated>0</truncated>
    <difficult>0</difficult>
    <bndbox>
        <xmin>375</xmin>
        <ymin>352</ymin>
        <xmax>494</xmax>
        <ymax>511</ymax>
    </bndbox>
</object>
    <object>
    <name>ProximalPhalanx</name>
    <pose>Unspecified</pose>
    <truncated>0</truncated>
    <difficult>0</difficult>
    <bndbox>
        <xmin>277</xmin>
        <ymin>383</ymin>
        <xmax>399</xmax>
        <ymax>542</ymax>
    </bndbox>
</object>
    <object>
    <name>ProximalPhalanx</name>
    <pose>Unspecified</pose>
    <truncated>0</truncated>
    <difficult>0</difficult>
    <bndbox>
        <xmin>172</xmin>
        <ymin>464</ymin>
        <xmax>290</xmax>
        <ymax>596</ymax>
    </bndbox>
</object>
    <object>
    <name>DistalPhalanx</name>
    <pose>Unspecified</pose>
    <truncated>0</truncated>
    <difficult>0</difficult>
    <bndbox>
        <xmin>696</xmin>
        <ymin>337</ymin>
        <xmax>838</xmax>
        <ymax>544</ymax>
    </bndbox>
</object>
    <object>
    <name>DistalPhalanx</name>
    <pose>Unspecified</pose>
    <truncated>0</truncated>
    <difficult>0</difficult>
    <bndbox>
        <xmin>548</xmin>
        <ymin>61</ymin>
        <xmax>663</xmax>
        <ymax>227</ymax>
    </bndbox>
</object>
    <object>
    <name>DistalPhalanx</name>
    <pose>Unspecified</pose>
    <truncated>0</truncated>
    <difficult>0</difficult>
    <bndbox>
        <xmin>402</xmin>
        <ymin>20</ymin>
        <xmax>527</xmax>
        <ymax>189</ymax>
    </bndbox>
</object>
    <object>
    <name>DistalPhalanx</name>
    <pose>Unspecified</pose>
    <truncated>0</truncated>
    <difficult>0</difficult>
    <bndbox>
        <xmin>266</xmin>
        <ymin>74</ymin>
        <xmax>372</xmax>
        <ymax>240</ymax>
    </bndbox>
</object>
    <object>
    <name>DistalPhalanx</name>
    <pose>Unspecified</pose>
    <truncated>0</truncated>
    <difficult>0</difficult>
    <bndbox>
        <xmin>107</xmin>
        <ymin>216</ymin>
        <xmax>243</xmax>
        <ymax>369</ymax>
    </bndbox>
</object>
    <object>
    <name>MiddlePhalanx</name>
    <pose>Unspecified</pose>
    <truncated>0</truncated>
    <difficult>0</difficult>
    <bndbox>
        <xmin>534</xmin>
        <ymin>244</ymin>
        <xmax>653</xmax>
        <ymax>342</ymax>
    </bndbox>
</object>
    <object>
    <name>MiddlePhalanx</name>
    <pose>Unspecified</pose>
    <truncated>0</truncated>
    <difficult>0</difficult>
    <bndbox>
        <xmin>392</xmin>
        <ymin>213</ymin>
        <xmax>507</xmax>
        <ymax>311</ymax>
    </bndbox>
</object>
    <object>
    <name>MiddlePhalanx</name>
    <pose>Unspecified</pose>
    <truncated>0</truncated>
    <difficult>0</difficult>
    <bndbox>
        <xmin>273</xmin>
        <ymin>267</ymin>
        <xmax>375</xmax>
        <ymax>355</ymax>
    </bndbox>
</object>
    <object>
    <name>MiddlePhalanx</name>
    <pose>Unspecified</pose>
    <truncated>0</truncated>
    <difficult>0</difficult>
    <bndbox>
        <xmin>138</xmin>
        <ymin>376</ymin>
        <xmax>263</xmax>
        <ymax>467</ymax>
    </bndbox>
</object>
</annotation>
