<?xml version="1.0" ?>
<annotation>
<folder>JPEGImages</folder>
<filename>6949.png</filename>
<path>E:\hand_bone_data\voc\VOCdevkit\VOC2007\JPEGImages\6949.png</path>
<source>
    <database>Unknown</database>
</source>
<size>
    <width>1123</width>
    <height>1361</height>
    <depth>3</depth>
</size>

<segmented>0</segmented>
    <object>
    <name>MiddlePhalanx</name>
    <pose>Unspecified</pose>
    <truncated>0</truncated>
    <difficult>0</difficult>
    <bndbox>
        <xmin>701</xmin>
        <ymin>284</ymin>
        <xmax>850</xmax>
        <ymax>440</ymax>
    </bndbox>
</object>
    <object>
    <name>MiddlePhalanx</name>
    <pose>Unspecified</pose>
    <truncated>0</truncated>
    <difficult>0</difficult>
    <bndbox>
        <xmin>549</xmin>
        <ymin>254</ymin>
        <xmax>688</xmax>
        <ymax>403</ymax>
    </bndbox>
</object>
    <object>
    <name>MiddlePhalanx</name>
    <pose>Unspecified</pose>
    <truncated>0</truncated>
    <difficult>0</difficult>
    <bndbox>
        <xmin>389</xmin>
        <ymin>315</ymin>
        <xmax>515</xmax>
        <ymax>454</ymax>
    </bndbox>
</object>
    <object>
    <name>MiddlePhalanx</name>
    <pose>Unspecified</pose>
    <truncated>0</truncated>
    <difficult>0</difficult>
    <bndbox>
        <xmin>220</xmin>
        <ymin>420</ymin>
        <xmax>352</xmax>
        <ymax>552</ymax>
    </bndbox>
</object>
    <object>
    <name>DistalPhalanx</name>
    <pose>Unspecified</pose>
    <truncated>0</truncated>
    <difficult>0</difficult>
    <bndbox>
        <xmin>155</xmin>
        <ymin>254</ymin>
        <xmax>328</xmax>
        <ymax>400</ymax>
    </bndbox>
</object>
    <object>
    <name>DistalPhalanx</name>
    <pose>Unspecified</pose>
    <truncated>0</truncated>
    <difficult>0</difficult>
    <bndbox>
        <xmin>379</xmin>
        <ymin>105</ymin>
        <xmax>501</xmax>
        <ymax>264</ymax>
    </bndbox>
</object>
    <object>
    <name>DistalPhalanx</name>
    <pose>Unspecified</pose>
    <truncated>0</truncated>
    <difficult>0</difficult>
    <bndbox>
        <xmin>552</xmin>
        <ymin>40</ymin>
        <xmax>654</xmax>
        <ymax>216</ymax>
    </bndbox>
</object>
    <object>
    <name>DistalPhalanx</name>
    <pose>Unspecified</pose>
    <truncated>0</truncated>
    <difficult>0</difficult>
    <bndbox>
        <xmin>752</xmin>
        <ymin>122</ymin>
        <xmax>874</xmax>
        <ymax>277</ymax>
    </bndbox>
</object>
    <object>
    <name>DistalPhalanx</name>
    <pose>Unspecified</pose>
    <truncated>0</truncated>
    <difficult>0</difficult>
    <bndbox>
        <xmin>898</xmin>
        <ymin>552</ymin>
        <xmax>1057</xmax>
        <ymax>762</ymax>
    </bndbox>
</object>
    <object>
    <name>ProximalPhalanx</name>
    <pose>Unspecified</pose>
    <truncated>0</truncated>
    <difficult>0</difficult>
    <bndbox>
        <xmin>650</xmin>
        <ymin>464</ymin>
        <xmax>779</xmax>
        <ymax>644</ymax>
    </bndbox>
</object>
    <object>
    <name>ProximalPhalanx</name>
    <pose>Unspecified</pose>
    <truncated>0</truncated>
    <difficult>0</difficult>
    <bndbox>
        <xmin>528</xmin>
        <ymin>457</ymin>
        <xmax>640</xmax>
        <ymax>616</ymax>
    </bndbox>
</object>
    <object>
    <name>ProximalPhalanx</name>
    <pose>Unspecified</pose>
    <truncated>0</truncated>
    <difficult>0</difficult>
    <bndbox>
        <xmin>406</xmin>
        <ymin>481</ymin>
        <xmax>518</xmax>
        <ymax>657</ymax>
    </bndbox>
</object>
    <object>
    <name>ProximalPhalanx</name>
    <pose>Unspecified</pose>
    <truncated>0</truncated>
    <difficult>0</difficult>
    <bndbox>
        <xmin>271</xmin>
        <ymin>545</ymin>
        <xmax>396</xmax>
        <ymax>684</ymax>
    </bndbox>
</object>
    <object>
    <name>ProximalPhalanx</name>
    <pose>Unspecified</pose>
    <truncated>0</truncated>
    <difficult>0</difficult>
    <bndbox>
        <xmin>806</xmin>
        <ymin>747</ymin>
        <xmax>959</xmax>
        <ymax>880</ymax>
    </bndbox>
</object>
    <object>
    <name>MCP</name>
    <pose>Unspecified</pose>
    <truncated>0</truncated>
    <difficult>0</difficult>
    <bndbox>
        <xmin>633</xmin>
        <ymin>596</ymin>
        <xmax>759</xmax>
        <ymax>783</ymax>
    </bndbox>
</object>
    <object>
    <name>MCP</name>
    <pose>Unspecified</pose>
    <truncated>0</truncated>
    <difficult>0</difficult>
    <bndbox>
        <xmin>515</xmin>
        <ymin>589</ymin>
        <xmax>623</xmax>
        <ymax>766</ymax>
    </bndbox>
</object>
    <object>
    <name>MCP</name>
    <pose>Unspecified</pose>
    <truncated>0</truncated>
    <difficult>0</difficult>
    <bndbox>
        <xmin>418</xmin>
        <ymin>616</ymin>
        <xmax>526</xmax>
        <ymax>806</ymax>
    </bndbox>
</object>
    <object>
    <name>MCP</name>
    <pose>Unspecified</pose>
    <truncated>0</truncated>
    <difficult>0</difficult>
    <bndbox>
        <xmin>308</xmin>
        <ymin>647</ymin>
        <xmax>413</xmax>
        <ymax>833</ymax>
    </bndbox>
</object>
    <object>
    <name>MCPFirst</name>
    <pose>Unspecified</pose>
    <truncated>0</truncated>
    <difficult>0</difficult>
    <bndbox>
        <xmin>608</xmin>
        <ymin>876</ymin>
        <xmax>801</xmax>
        <ymax>1089</ymax>
    </bndbox>
</object>
    <object>
    <name>Ulna</name>
    <pose>Unspecified</pose>
    <truncated>0</truncated>
    <difficult>0</difficult>
    <bndbox>
        <xmin>294</xmin>
        <ymin>1088</ymin>
        <xmax>423</xmax>
        <ymax>1294</ymax>
    </bndbox>
</object>
    <object>
    <name>Radius</name>
    <pose>Unspecified</pose>
    <truncated>0</truncated>
    <difficult>0</difficult>
    <bndbox>
        <xmin>400</xmin>
        <ymin>1101</ymin>
        <xmax>627</xmax>
        <ymax>1332</ymax>
    </bndbox>
</object>
</annotation>
